full_adder.v
module full_adder(a,b,c,sum,carry);
    input a,b,c;
    output sum,carry;
    assign sum=a^b^c;
    assign carry=(a&b)+(a&c)+(b&c);
endmodule

full_adder_tb.v
//`include "full_adder.v"
module full_adder_tb;
    reg a,b,c;
    wire sum,carry;
    full_adder add(a,b,c,sum,carry);
    initial 
    begin
        $dumpfile("full_adder_tb.vcd");
        $dumpvars(0,full_adder_tb);
        $monitor("a = %b, b = %b, c = %b, sum = %b carry = %b\n",a,b,c,sum,carry);
        a = 0;
        b = 0;
        c = 0;
        #5;
        a = 0;
        b = 0;
        c = 1;
        #5;
        a = 0;
        b = 1;
        c = 0;
        #5;
        a = 0;
        b = 1;
        c = 1;
        #5;
        a = 1;
        b = 0;
        c = 0;
        #5;
        a = 1;
        b = 0;
        c = 1;
        #5;
        a = 1;
        b = 1;
        c = 0;
        #5;
        a = 1;
        b = 1;
        c = 1;
        #5;
    end
endmodule

full_adder_tb.vcd
$date
	Thu Jul 28 11:37:20 2022
$end
$version
	Icarus Verilog
$end
$timescale
	1s
$end
$scope module full_adder_tb $end
$var wire 1 ! sum $end
$var wire 1 " carry $end
$var reg 1 # a $end
$var reg 1 $ b $end
$var reg 1 % c $end
$scope module add $end
$var wire 1 # a $end
$var wire 1 $ b $end
$var wire 1 % c $end
$var wire 1 ! sum $end
$var wire 1 " carry $end
$upscope $end
$upscope $end
$enddefinitions $end
$comment Show the parameter values. $end
$dumpall
$end
#0
$dumpvars
0%
0$
0#
0"
0!
$end
#5
1!
1%
#10
0%
1$
#15
0!
1"
1%
#20
1!
0"
0%
0$
1#
#25
0!
1"
1%
#30
1"
0%
1$
#35
1!
1"
1%
